asciidocbuilder/__init__.py
asciidocbuilder/core/__init__.py
asciidocbuilder/core/base_elements.py
asciidocbuilder/core/builder.py
asciidocbuilder/elements/__init__.py
asciidocbuilder/elements/admonition.py
asciidocbuilder/elements/list.py
asciidocbuilder/elements/media.py
asciidocbuilder/elements/structure.py
asciidocbuilder/elements/text.py
asciidocbuilder/examples/__init__.py
asciidocbuilder/examples/simple_document.py
asciidocbuilder/utils/__init__.py
asciidocbuilder/utils/helpers.py
asciidocbuilder-0.1.1.dist-info/METADATA
asciidocbuilder-0.1.1.dist-info/WHEEL
asciidocbuilder-0.1.1.dist-info/RECORD
