Metadata-Version: 2.1
Name: asciidocbuilder
Version: 0.1.1
Summary: 
Author: Pedro Vidigal
Author-email: vidigal.pedro@gmail.com
Requires-Python: >=3.9,<4.0
Classifier: Programming Language :: Python :: 3
Classifier: Programming Language :: Python :: 3.9
Classifier: Programming Language :: Python :: 3.10
Classifier: Programming Language :: Python :: 3.11
Requires-Dist: black (>=23.9.1,<24.0.0)
Requires-Dist: pendulum (>=2.1.2,<3.0.0)
Requires-Dist: pip-tools (>=7.3.0,<8.0.0)
Requires-Dist: pytest (>=7.4.2,<8.0.0)
